davinciGPT/__init__.py
davinciGPT/main.py
davinciGPT-1.0.1.dist-info/LICENSE
davinciGPT-1.0.1.dist-info/METADATA
davinciGPT-1.0.1.dist-info/WHEEL
davinciGPT-1.0.1.dist-info/top_level.txt
davinciGPT-1.0.1.dist-info/RECORD
